engawa/.null-ls_883731_cli.py
engawa/.null-ls_893613_train.py
engawa/__init__.py
engawa/cli.py
engawa/data_collator.py
engawa/data_loader.py
engawa/misc/did_it_learn_anything.py
engawa/model.py
engawa/tokenizer.py
engawa/train.py
engawa-0.1.5.dist-info/entry_points.txt
engawa-0.1.5.dist-info/WHEEL
engawa-0.1.5.dist-info/METADATA
engawa-0.1.5.dist-info/RECORD
